ledger_app_clients/exchange/__init__.py
ledger_app_clients/exchange/cal_helper.py
ledger_app_clients/exchange/client.py
ledger_app_clients/exchange/ethereum.py
ledger_app_clients/exchange/navigation_helper.py
ledger_app_clients/exchange/signing_authority.py
ledger_app_clients/exchange/test_runner.py
ledger_app_clients/exchange/transaction_builder.py
ledger_app_clients/exchange/utils.py
ledger_app_clients/exchange/pb/__init__.py
ledger_app_clients/exchange/pb/exchange_pb2.py
ledger_app_clients/exchange/pki/__init__.py
ledger_app_clients/exchange/pki/pem_signer.py
ledger_app_clients/exchange/pki/tlv.py
ledger_app_clients/exchange/pki/trusted_name.pem
ledger_app_clients_exchange-0.1.0.dist-info/licenses/LICENSE
ledger_app_clients_exchange-0.1.0.dist-info/METADATA
ledger_app_clients_exchange-0.1.0.dist-info/WHEEL
ledger_app_clients_exchange-0.1.0.dist-info/top_level.txt
ledger_app_clients_exchange-0.1.0.dist-info/RECORD
