Metadata-Version: 2.4
Name: ledger_app_clients.exchange
Version: 0.1.0
Summary: Ledger Exchange Python client
Author-email: Ledger <hello@ledger.fr>
Project-URL: Homepage, https://github.com/LedgerHQ/app-exchange
Project-URL: Issues, https://github.com/LedgerHQ/app-exchange/issues
Classifier: Programming Language :: Python :: 3
Classifier: Operating System :: OS Independent
License-File: LICENSE
Requires-Dist: ragger
Requires-Dist: cryptography
Dynamic: license-file
